flask_frozen/__init__.py
flask_frozen/tests.py
flask_frozen/test_app/__init__.py
flask_frozen/test_app/admin/__init__.py
flask_frozen/test_app/admin/admin_static/style.css
flask_frozen/test_app/admin/templates/admin.html
flask_frozen/test_app/static/favicon.ico
flask_frozen/test_app/static/main.js
flask_frozen/test_app/static/style.css
Frozen_Flask-0.19.dist-info/AUTHORS
Frozen_Flask-0.19.dist-info/LICENSE
Frozen_Flask-0.19.dist-info/METADATA
Frozen_Flask-0.19.dist-info/WHEEL
Frozen_Flask-0.19.dist-info/top_level.txt
Frozen_Flask-0.19.dist-info/RECORD
